{
  "version": "4.5.6",
  "flags": {
    "done": true,
    "review": false,
    "others": false,
    "login": false,
    "account_creation": false,
    "product_listing": false,
    "product_description": true,
    "splash": false
  },
  "shapes": [
    {
      "element": "android.support.v7.widget.AppCompatTextView",
      "class": "android.support.v7.view.menu.ActionMenuItemView",
      "text": "",
      "label": "search_button",
      "points": [
        [
          281.25,
          24.5
        ],
        [
          323.25,
          66.5
        ]
      ],
      "group_id": 12,
      "shape_type": "rectangle",
      "flags": {}
    },
    {
      "element": "android.widget.ImageView",
      "class": "android.support.v7.widget.AppCompatImageView",
      "text": "",
      "label": "cart_icon_button",
      "points": [
        [
          327.5,
          31.5
        ],
        [
          355.5,
          59.5
        ]
      ],
      "group_id": 13,
      "shape_type": "rectangle",
      "flags": {}
    },
    {
      "element": "android.widget.ImageButton",
      "class": "android.support.v7.widget.AppCompatImageButton",
      "text": "",
      "label": "menu_dashs",
      "points": [
        [
          0.0,
          21.0
        ],
        [
          49.0,
          70.0
        ]
      ],
      "group_id": 11,
      "shape_type": "rectangle",
      "flags": {}
    },
    {
      "element": "android.widget.TextView",
      "class": "android.support.v7.widget.AppCompatTextView",
      "text": "Product Details",
      "label": "text_view",
      "points": [
        [
          63.0,
          33.75
        ],
        [
          183.5,
          57.0
        ]
      ],
      "group_id": 11,
      "shape_type": "rectangle",
      "flags": {
        "use_class": true
      }
    },
    {
      "element": "android.widget.ImageView",
      "class": "android.support.v7.widget.AppCompatImageView",
      "text": "",
      "label": "ad",
      "points": [
        [
          0.0,
          70.0
        ],
        [
          360.0,
          112.0
        ]
      ],
      "group_id": 23,
      "shape_type": "rectangle",
      "flags": {}
    },
    {
      "element": "android.widget.TextView",
      "class": "com.fanatics.fanatics_android_sdk.ui.views.FanaticsTextView",
      "text": "Dallas Cowboys Youth Practice Fleece Hoodie - Navy Blue",
      "label": "text_view",
      "points": [
        [
          15.75,
          342.5
        ],
        [
          344.25,
          382.0
        ]
      ],
      "group_id": 26,
      "shape_type": "rectangle",
      "flags": {
        "use_class": true
      }
    },
    {
      "element": "android.widget.TextView",
      "class": "com.fanatics.fanatics_android_sdk.ui.views.FanaticsTextView",
      "text": "In Stock",
      "label": "text_view",
      "points": [
        [
          15.75,
          386.5
        ],
        [
          69.25,
          406.75
        ]
      ],
      "group_id": 26,
      "shape_type": "rectangle",
      "flags": {
        "use_class": true
      }
    },
    {
      "element": "android.widget.TextView",
      "class": "com.fanatics.fanatics_android_sdk.ui.views.FanaticsTextView",
      "text": "$29.99",
      "label": "price",
      "points": [
        [
          15.75,
          411.25
        ],
        [
          62.5,
          431.5
        ]
      ],
      "group_id": 27,
      "shape_type": "rectangle",
      "flags": {
        "use_class": true
      }
    },
    {
      "element": "java.lang.Object",
      "class": "android.view.View",
      "text": "",
      "label": "separator_line",
      "points": [
        [
          0.0,
          444.75
        ],
        [
          360.0,
          445.75
        ]
      ],
      "group_id": 26,
      "shape_type": "rectangle",
      "flags": {
        "use_class": true
      }
    },
    {
      "element": "android.widget.TextView",
      "class": "com.fanatics.fanatics_android_sdk.ui.views.FanaticsTextView",
      "text": "SIZE CHART",
      "label": "text_view",
      "points": [
        [
          277.5,
          454.5
        ],
        [
          344.25,
          471.0
        ]
      ],
      "group_id": 32,
      "shape_type": "rectangle",
      "flags": {
        "use_class": true
      }
    },
    {
      "element": "android.widget.ImageView",
      "class": "android.support.v7.widget.AppCompatImageView",
      "text": "",
      "label": "image_view",
      "points": [
        [
          260.5,
          457.25
        ],
        [
          277.5,
          468.0
        ]
      ],
      "group_id": 32,
      "shape_type": "rectangle",
      "flags": {
        "use_class": true
      }
    },
    {
      "element": "android.widget.RadioButton",
      "class": "com.fanatics.fanatics_android_sdk.ui.views.FanaticsSizeRadioButton",
      "text": "Yth S",
      "label": "radio_button",
      "points": [
        [
          15.75,
          479.75
        ],
        [
          77.0,
          514.75
        ]
      ],
      "group_id": 33,
      "shape_type": "rectangle",
      "flags": {
        "use_class": true
      }
    },
    {
      "element": "android.widget.RadioButton",
      "class": "com.fanatics.fanatics_android_sdk.ui.views.FanaticsSizeRadioButton",
      "text": "Yth M",
      "label": "radio_button",
      "points": [
        [
          81.5,
          479.75
        ],
        [
          142.75,
          514.75
        ]
      ],
      "group_id": 33,
      "shape_type": "rectangle",
      "flags": {
        "use_class": true
      }
    },
    {
      "element": "android.widget.RadioButton",
      "class": "com.fanatics.fanatics_android_sdk.ui.views.FanaticsSizeRadioButton",
      "text": "Yth L",
      "label": "radio_button",
      "points": [
        [
          147.25,
          479.75
        ],
        [
          208.5,
          514.75
        ]
      ],
      "group_id": 33,
      "shape_type": "rectangle",
      "flags": {
        "use_class": true
      }
    },
    {
      "element": "android.widget.RadioButton",
      "class": "com.fanatics.fanatics_android_sdk.ui.views.FanaticsSizeRadioButton",
      "text": "Yth XL",
      "label": "radio_button",
      "points": [
        [
          213.0,
          479.75
        ],
        [
          274.25,
          514.75
        ]
      ],
      "group_id": 33,
      "shape_type": "rectangle",
      "flags": {
        "use_class": true
      }
    },
    {
      "element": "java.lang.Object",
      "class": "android.view.View",
      "text": "",
      "label": "separator_line",
      "points": [
        [
          0.0,
          532.25
        ],
        [
          360.0,
          533.25
        ]
      ],
      "group_id": 26,
      "shape_type": "rectangle",
      "flags": {
        "use_class": true
      }
    },
    {
      "element": "java.lang.Object",
      "class": "android.view.View",
      "text": "",
      "label": "separator_line",
      "points": [
        [
          0.0,
          533.25
        ],
        [
          360.0,
          534.25
        ]
      ],
      "group_id": 26,
      "shape_type": "rectangle",
      "flags": {
        "use_class": true
      }
    },
    {
      "element": "android.widget.ImageView",
      "class": "android.support.v7.widget.AppCompatImageView",
      "text": "",
      "label": "image_view",
      "points": [
        [
          0.0,
          112.0
        ],
        [
          360.0,
          330.75
        ]
      ],
      "group_id": 73,
      "shape_type": "rectangle",
      "flags": {
        "use_class": true
      }
    },
    {
      "element": "android.widget.ImageView",
      "class": "android.support.v7.widget.AppCompatImageView",
      "text": "",
      "label": "share_button",
      "points": [
        [
          317.5,
          120.75
        ],
        [
          344.25,
          147.5
        ]
      ],
      "group_id": 26,
      "shape_type": "rectangle",
      "flags": {}
    },
    {
      "element": "android.widget.ImageView",
      "class": "android.support.v7.widget.AppCompatImageView",
      "text": "",
      "label": "image_view",
      "points": [
        [
          331.0,
          325.25
        ],
        [
          344.25,
          338.5
        ]
      ],
      "group_id": 26,
      "shape_type": "rectangle",
      "flags": {
        "use_class": true
      }
    },
    {
      "element": "android.view.View",
      "class": "android.widget.ImageView",
      "text": "",
      "label": "navigation_dots",
      "points": [
        [
          162.5,
          335.25
        ],
        [
          199.33333333333334,
          339.0
        ]
      ],
      "group_id": 76,
      "shape_type": "rectangle",
      "flags": {}
    },
    {
      "element": "android.widget.TextView",
      "class": "com.fanatics.fanatics_android_sdk.ui.views.FanaticsTextView",
      "text": "ADD TO CART",
      "label": "cart_add",
      "points": [
        [
          16.0,
          545.0
        ],
        [
          344.6666666666667,
          589.6666666666666
        ]
      ],
      "group_id": 80,
      "shape_type": "rectangle",
      "flags": {}
    },
    {
      "label": "size_picker",
      "points": [
        [
          13.333333333333332,
          477.6666666666667
        ],
        [
          343.3333333333333,
          516.3333333333334
        ]
      ],
      "group_id": null,
      "shape_type": "rectangle",
      "flags": {}
    },
    {
      "element": "android.widget.RadioButton",
      "class": "com.fanatics.fanatics_android_sdk.ui.views.FanaticsSizeRadioButton",
      "text": "Yth XL",
      "label": "radio_button",
      "points": [
        [
          278.3333333333333,
          480.41666666666663
        ],
        [
          339.5833333333334,
          515.4166666666666
        ]
      ],
      "group_id": 33,
      "shape_type": "rectangle",
      "flags": {
        "use_class": true
      }
    }
  ],
  "imagePath": "23361.jpg",
  "imageData": null,
  "imageHeight": 640,
  "imageWidth": 360
}