{
 "version": "4.2.10",
 "flags": {
  "done": true,
  "others": false,
  "login": false,
  "account_creation": false,
  "product_listing": false,
  "product_description": false,
  "splash": true,
  "review": false
 },
 "shapes": [
  {
   "element": "android.widget.TextView",
   "class": "android.support.v7.widget.aa",
   "text": "Stay up to date on new car launches, upcoming cars and latest happenings in the automobile circuit.",
   "label": "text_view",
   "points": [
    [
     0.0,
     296.0
    ],
    [
     359.0,
     359.0
    ]
   ],
   "group_id": 16,
   "shape_type": "rectangle",
   "flags": {
    "use_class": true
   }
  },
  {
   "element": "android.widget.TextView",
   "class": "android.support.v7.widget.aa",
   "text": "Skip",
   "label": "text_view",
   "points": [
    [
     4.5,
     29.75
    ],
    [
     79.0,
     74.33333333333333
    ]
   ],
   "group_id": 11,
   "shape_type": "rectangle",
   "flags": {
    "use_class": true
   }
  },
  {
   "element": "android.widget.TextView",
   "class": "android.support.v7.widget.aa",
   "text": "Sign in to get best Experience with",
   "label": "text_view",
   "points": [
    [
     17.5,
     466.25
    ],
    [
     273.0,
     484.3333333333333
    ]
   ],
   "group_id": 20,
   "shape_type": "rectangle",
   "flags": {
    "use_class": true
   }
  },
  {
   "element": "android.widget.Button",
   "class": "android.support.v7.widget.h",
   "text": "Sign in with Facebook",
   "label": "fb_button",
   "points": [
    [
     8.75,
     492.75
    ],
    [
     175.5,
     536.5
    ]
   ],
   "group_id": 21,
   "shape_type": "rectangle",
   "flags": {}
  },
  {
   "element": "android.widget.Button",
   "class": "android.support.v7.widget.h",
   "text": "Sign in with Google+",
   "label": "google_button",
   "points": [
    [
     184.5,
     492.75
    ],
    [
     351.25,
     536.5
    ]
   ],
   "group_id": 21,
   "shape_type": "rectangle",
   "flags": {}
  },
  {
   "element": "android.widget.TextView",
   "class": "android.support.v7.widget.aa",
   "text": "Already have an account?",
   "label": "text_view",
   "points": [
    [
     73.75,
     554.0
    ],
    [
     224.25,
     571.75
    ]
   ],
   "group_id": 22,
   "shape_type": "rectangle",
   "flags": {
    "use_class": true
   }
  },
  {
   "element": "android.widget.TextView",
   "class": "android.support.v7.widget.aa",
   "text": "Sign in Now",
   "label": "text_view",
   "points": [
    [
     233.0,
     554.0
    ],
    [
     303.75,
     571.75
    ]
   ],
   "group_id": 22,
   "shape_type": "rectangle",
   "flags": {
    "use_class": true
   }
  },
  {
   "element": "android.widget.ImageView",
   "class": "android.support.v7.widget.p",
   "text": "",
   "label": "navigation_dots",
   "points": [
    [
     157.0,
     447.6666666666667
    ],
    [
     202.33333333333334,
     459.6666666666667
    ]
   ],
   "group_id": 23,
   "shape_type": "rectangle",
   "flags": {}
  }
 ],
 "imagePath": "10541.jpg",
 "imageData": null,
 "imageHeight": 640,
 "imageWidth": 360
}