{
 "version": "4.2.10",
 "flags": {
  "done": true,
  "others": false,
  "login": false,
  "account_creation": false,
  "product_listing": false,
  "product_description": false,
  "splash": true,
  "review": false
 },
 "shapes": [
  {
   "element": "android.widget.ImageView",
   "class": "android.support.v7.widget.AppCompatImageView",
   "text": "",
   "label": "image_view",
   "points": [
    [
     127.5,
     92.5
    ],
    [
     232.5,
     197.5
    ]
   ],
   "group_id": 7,
   "shape_type": "rectangle",
   "flags": {
    "use_class": true
   }
  },
  {
   "element": "android.widget.ImageView",
   "class": "android.support.v7.widget.AppCompatImageView",
   "text": "",
   "label": "image_view",
   "points": [
    [
     6.25,
     218.5
    ],
    [
     353.75,
     237.75
    ]
   ],
   "group_id": 7,
   "shape_type": "rectangle",
   "flags": {
    "use_class": true
   }
  },
  {
   "element": "android.widget.Button",
   "class": "android.support.v7.widget.AppCompatButton",
   "text": "Create a wallet",
   "label": "sign_up",
   "points": [
    [
     73.25,
     316.5
    ],
    [
     286.5,
     365.75
    ]
   ],
   "group_id": 8,
   "shape_type": "rectangle",
   "flags": {
    "use_class": true
   }
  },
  {
   "element": "android.widget.Button",
   "class": "android.support.v7.widget.AppCompatButton",
   "text": "Log in",
   "label": "log_in",
   "points": [
    [
     73.25,
     379.75
    ],
    [
     286.5,
     429.0
    ]
   ],
   "group_id": 8,
   "shape_type": "rectangle",
   "flags": {}
  },
  {
   "element": "android.widget.TextView",
   "class": "android.support.v7.widget.AppCompatTextView",
   "text": "Recover Funds",
   "label": "text_view",
   "points": [
    [
     73.25,
     443.0
    ],
    [
     286.5,
     464.25
    ]
   ],
   "group_id": 8,
   "shape_type": "rectangle",
   "flags": {
    "use_class": true
   }
  }
 ],
 "imagePath": "12951.jpg",
 "imageData": null,
 "imageHeight": 640,
 "imageWidth": 360
}