{
 "shapes": [
  {
   "points": [
    [
     260,
     566
    ],
    [
     347,
     568
    ]
   ],
   "label": "image"
  },
  {
   "points": [
    [
     16,
     566
    ],
    [
     63,
     568
    ]
   ],
   "label": "image"
  },
  {
   "points": [
    [
     129,
     565
    ],
    [
     234,
     569
    ]
   ],
   "label": "image"
  },
  {
   "points": [
    [
     272,
     486
    ],
    [
     318,
     535
    ]
   ],
   "label": "image"
  },
  {
   "points": [
    [
     196,
     486
    ],
    [
     243,
     535
    ]
   ],
   "label": "image"
  },
  {
   "points": [
    [
     121,
     486
    ],
    [
     167,
     535
    ]
   ],
   "label": "image"
  },
  {
   "points": [
    [
     45,
     486
    ],
    [
     91,
     535
    ]
   ],
   "label": "image"
  },
  {
   "points": [
    [
     187,
     308
    ],
    [
     285,
     333
    ]
   ],
   "label": "sign_up"
  },
  {
   "points": [
    [
     78,
     308
    ],
    [
     175,
     333
    ]
   ],
   "label": "log_in"
  },
  {
   "points": [
    [
     122,
     259
    ],
    [
     241,
     292
    ]
   ],
   "label": "check"
  },
  {
   "points": [
    [
     76,
     5
    ],
    [
     288,
     136
    ]
   ],
   "label": "image"
  }
 ],
 "imageHeight": 567,
 "imageWidth": 360,
 "flags": {
  "login": true
 }
}