{
 "shapes": [
  {
   "points": [
    [
     96,
     335
    ],
    [
     152,
     356
    ]
   ],
   "label": "button"
  },
  {
   "points": [
    [
     25,
     334
    ],
    [
     81,
     356
    ]
   ],
   "label": "log_in"
  },
  {
   "points": [
    [
     111,
     284
    ],
    [
     140,
     293
    ]
   ],
   "label": "forgot"
  },
  {
   "points": [
    [
     23,
     283
    ],
    [
     97,
     292
    ]
   ],
   "label": "check"
  },
  {
   "points": [
    [
     25,
     247
    ],
    [
     157,
     264
    ]
   ],
   "label": "password"
  },
  {
   "points": [
    [
     25,
     207
    ],
    [
     156,
     224
    ]
   ],
   "label": "username"
  },
  {
   "points": [
    [
     223,
     66
    ],
    [
     274,
     120
    ]
   ],
   "label": "image"
  },
  {
   "points": [
    [
     251,
     17
    ],
    [
     339,
     27
    ]
   ],
   "label": "sign_up"
  },
  {
   "points": [
    [
     15,
     5
    ],
    [
     41,
     37
    ]
   ],
   "label": "image"
  }
 ],
 "imageHeight": 567,
 "imageWidth": 360,
 "flags": {
  "login": true
 }
}