{
 "version": "4.2.10",
 "flags": {
  "done": true,
  "others": false,
  "login": false,
  "account_creation": true,
  "product_listing": false,
  "product_description": false,
  "splash": false,
  "review": false
 },
 "shapes": [
  {
   "element": "android.widget.TextView",
   "class": "com.fiserv.popmoney.customwidgets.CustomTextview",
   "text": "Create a profile",
   "label": "text_view",
   "points": [
    [
     120.0,
     64.75
    ],
    [
     239.75,
     92.25
    ]
   ],
   "group_id": 5,
   "shape_type": "rectangle",
   "flags": {
    "use_class": true
   }
  },
  {
   "element": "android.widget.TextView",
   "class": "com.fiserv.popmoney.customwidgets.CustomTextview",
   "text": "appcrawler4@gmail.com will be your login id.",
   "label": "text_view",
   "points": [
    [
     47.0,
     109.75
    ],
    [
     312.75,
     130.75
    ]
   ],
   "group_id": 5,
   "shape_type": "rectangle",
   "flags": {
    "use_class": true
   }
  },
  {
   "element": "android.widget.EditText",
   "class": "com.fiserv.popmoney.customwidgets.CustomEdittext",
   "text": "First name",
   "label": "name",
   "points": [
    [
     17.5,
     155.25
    ],
    [
     177.75,
     189.5
    ]
   ],
   "group_id": 7,
   "shape_type": "rectangle",
   "flags": {
    "use_class": true
   }
  },
  {
   "element": "android.widget.EditText",
   "class": "com.fiserv.popmoney.customwidgets.CustomEdittext",
   "text": "Last name",
   "label": "last_name",
   "points": [
    [
     182.25,
     155.25
    ],
    [
     342.5,
     189.5
    ]
   ],
   "group_id": 7,
   "shape_type": "rectangle",
   "flags": {
    "use_class": true
   }
  },
  {
   "element": "android.widget.EditText",
   "class": "com.fiserv.popmoney.customwidgets.CustomEdittext",
   "text": "Mobile number",
   "label": "phone_number",
   "points": [
    [
     17.5,
     198.25
    ],
    [
     342.5,
     232.5
    ]
   ],
   "group_id": 5,
   "shape_type": "rectangle",
   "flags": {
    "use_class": true
   }
  },
  {
   "element": "android.widget.EditText",
   "class": "com.fiserv.popmoney.customwidgets.CustomEdittext",
   "text": "Create password",
   "label": "password",
   "points": [
    [
     17.5,
     241.25
    ],
    [
     342.5,
     275.5
    ]
   ],
   "group_id": 8,
   "shape_type": "rectangle",
   "flags": {
    "use_class": true
   }
  },
  {
   "element": "android.view.View",
   "class": "android.widget.ImageView",
   "text": "",
   "label": "icon_button",
   "points": [
    [
     320.5,
     248.5
    ],
    [
     333.75,
     268.25
    ]
   ],
   "group_id": 8,
   "shape_type": "rectangle",
   "flags": {}
  }
 ],
 "imagePath": "10279.jpg",
 "imageData": null,
 "imageHeight": 640,
 "imageWidth": 360
}