{
 "shapes": [
  {
   "points": [
    [
     255,
     541
    ],
    [
     348,
     570
    ]
   ],
   "label": "button"
  },
  {
   "points": [
    [
     134,
     541
    ],
    [
     231,
     570
    ]
   ],
   "label": "sort"
  },
  {
   "points": [
    [
     149,
     499
    ],
    [
     189,
     507
    ]
   ],
   "label": "rating"
  },
  {
   "points": [
    [
     12,
     474
    ],
    [
     127,
     572
    ]
   ],
   "label": "image"
  },
  {
   "points": [
    [
     148,
     437
    ],
    [
     201,
     448
    ]
   ],
   "label": "number"
  },
  {
   "points": [
    [
     305,
     434
    ],
    [
     323,
     452
    ]
   ],
   "label": "image"
  },
  {
   "points": [
    [
     149,
     366
    ],
    [
     189,
     374
    ]
   ],
   "label": "rating"
  },
  {
   "points": [
    [
     16,
     341
    ],
    [
     127,
     455
    ]
   ],
   "label": "image"
  },
  {
   "points": [
    [
     148,
     304
    ],
    [
     191,
     315
    ]
   ],
   "label": "number"
  },
  {
   "points": [
    [
     305,
     299
    ],
    [
     323,
     317
    ]
   ],
   "label": "image"
  },
  {
   "points": [
    [
     149,
     233
    ],
    [
     189,
     241
    ]
   ],
   "label": "rating"
  },
  {
   "points": [
    [
     16,
     208
    ],
    [
     127,
     322
    ]
   ],
   "label": "image"
  },
  {
   "points": [
    [
     148,
     171
    ],
    [
     201,
     182
    ]
   ],
   "label": "number"
  },
  {
   "points": [
    [
     305,
     168
    ],
    [
     323,
     186
    ]
   ],
   "label": "image"
  },
  {
   "points": [
    [
     149,
     100
    ],
    [
     189,
     108
    ]
   ],
   "label": "rating"
  },
  {
   "points": [
    [
     16,
     75
    ],
    [
     127,
     189
    ]
   ],
   "label": "image"
  },
  {
   "points": [
    [
     8,
     5
    ],
    [
     45,
     45
    ]
   ],
   "label": "icon"
  }
 ],
 "imageHeight": 567,
 "imageWidth": 360,
 "flags": {
  "product_listing": true
 }
}